mseep_yaraflux_mcp_server-1.0.18.dist-info/licenses/LICENSE
yaraflux_mcp_server/__init__.py
yaraflux_mcp_server/__main__.py
yaraflux_mcp_server/app.py
yaraflux_mcp_server/auth.py
yaraflux_mcp_server/claude_mcp.py
yaraflux_mcp_server/claude_mcp_tools.py
yaraflux_mcp_server/config.py
yaraflux_mcp_server/mcp_server.py
yaraflux_mcp_server/models.py
yaraflux_mcp_server/run_mcp.py
yaraflux_mcp_server/yara_service.py
yaraflux_mcp_server/routers/__init__.py
yaraflux_mcp_server/routers/auth.py
yaraflux_mcp_server/routers/files.py
yaraflux_mcp_server/routers/rules.py
yaraflux_mcp_server/routers/scan.py
mseep_yaraflux_mcp_server-1.0.18.dist-info/METADATA
mseep_yaraflux_mcp_server-1.0.18.dist-info/WHEEL
mseep_yaraflux_mcp_server-1.0.18.dist-info/entry_points.txt
mseep_yaraflux_mcp_server-1.0.18.dist-info/top_level.txt
mseep_yaraflux_mcp_server-1.0.18.dist-info/RECORD
