Metadata-Version: 2.4
Name: mseep-yaraflux_mcp_server
Version: 1.0.18
Summary: Model Context Protocol (MCP) server for YARA scanning
Author-email: mseep <support@skydeck.ai>
Project-URL: Homepage, https://github.com/ThreatFlux/YaraFlux
Project-URL: Bug Tracker, https://github.com/ThreatFlux/YaraFlux/issues
Classifier: Development Status :: 4 - Beta
Classifier: Intended Audience :: Developers
Classifier: License :: OSI Approved :: MIT License
Classifier: Programming Language :: Python :: 3
Classifier: Programming Language :: Python :: 3.13
Requires-Python: >=3.13
License-File: LICENSE
Requires-Dist: fastapi>=0.110.0
Requires-Dist: uvicorn[standard]>=0.27.0
Requires-Dist: pydantic>=2.6.0
Requires-Dist: pydantic-settings>=2.1.0
Requires-Dist: yara-python>=4.5.0
Requires-Dist: httpx>=0.27.0
Requires-Dist: python-jose[cryptography]>=3.3.0
Requires-Dist: passlib[bcrypt]>=1.7.4
Requires-Dist: python-multipart>=0.0.7
Requires-Dist: python-dotenv>=1.0.0
Requires-Dist: mcp>=1.3.0
Requires-Dist: click>=8.1.7
Requires-Dist: minio>=7.2.15
Provides-Extra: dev
Requires-Dist: pytest>=8.0.0; extra == "dev"
Requires-Dist: pytest-asyncio>=0.23.0; extra == "dev"
Requires-Dist: pytest-cov>=4.1.0; extra == "dev"
Requires-Dist: black>=24.1.0; extra == "dev"
Requires-Dist: isort>=5.13.0; extra == "dev"
Requires-Dist: pylint>=3.0.0; extra == "dev"
Requires-Dist: mypy>=1.8.0; extra == "dev"
Requires-Dist: bandit>=1.7.0; extra == "dev"
Requires-Dist: safety>=3.0.0; extra == "dev"
Requires-Dist: coverage>=7.6.12; extra == "dev"
Requires-Dist: pre-commit>=3.6.0; extra == "dev"
Requires-Dist: wheel>=0.45.0; extra == "dev"
Dynamic: license-file
